graphpy/__init__.py
graphpy/edge.py
graphpy/graph.py
graphpy/helpers.py
graphpy/vertex.py
graphpy-1.1.0.dist-info/DESCRIPTION.rst
graphpy-1.1.0.dist-info/METADATA
graphpy-1.1.0.dist-info/RECORD
graphpy-1.1.0.dist-info/WHEEL
graphpy-1.1.0.dist-info/metadata.json
graphpy-1.1.0.dist-info/top_level.txt
tests/__init__.py
tests/test_edge.py
tests/test_graph.py
tests/test_helpers.py
tests/test_vertex.py
