Metadata-Version: 2.0
Name: graphpy
Version: 1.1.0
Summary: A Python implementation of a edges, vertices, and graphs
Home-page: https://github.com/tscizzle/graphpy
Author: Tyler Singer-Clark
Author-email: tscizzle@gmail.com
License: MIT
Keywords: edge vertex graph
Platform: UNKNOWN
Classifier: Intended Audience :: Developers
Classifier: Topic :: Scientific/Engineering
Classifier: License :: OSI Approved :: MIT License
Classifier: Programming Language :: Python :: 2
